nonebot_plugin_any/__init__.py
nonebot_plugin_any/adapters/kook.py
nonebot_plugin_any/adapters/onebot.py
nonebot_plugin_any/adapters/qq.py
nonebot_plugin_any/adapters/qqguild.py
nonebot_plugin_any/event.py
nonebot_plugin_any/message.py
nonebot_plugin_any/models.py
nonebot_plugin_any/patch.py
nonebot_plugin_any/utils/__init__.py
nonebot_plugin_any/utils/requests.py
nonebot_plugin_any-0.2.0.dist-info/LICENSE
nonebot_plugin_any-0.2.0.dist-info/METADATA
nonebot_plugin_any-0.2.0.dist-info/WHEEL
nonebot_plugin_any-0.2.0.dist-info/RECORD
