Metadata-Version: 2.1
Name: nonebot-plugin-any
Version: 0.2.0
Summary: NoneBot2 多平台统一事件与统一消息构造发送
License: MIT
Author: Melody_Yuuka
Author-email: a876987@126.com
Requires-Python: >=3.10
Classifier: License :: OSI Approved :: MIT License
Classifier: Programming Language :: Python :: 3
Classifier: Programming Language :: Python :: 3.10
Classifier: Programming Language :: Python :: 3.11
Classifier: Programming Language :: Python :: 3.12
Requires-Dist: httpx (>=0.20.0,<1.0.0)
Requires-Dist: nonebot2 (>=2.1.0)
Requires-Dist: typing-extensions (>=4.5.0)
